CHANGES.txt
LICENSE.txt
MANIFEST.in
README.rst
README.txt
setup.py
GoreUtilities/__init__.py
GoreUtilities/_version.py
GoreUtilities/backup_util.py
GoreUtilities/dialogs.py
GoreUtilities/docstring.py
GoreUtilities/graph.py
GoreUtilities/simulation.py
GoreUtilities/util.py
GoreUtilities.egg-info/PKG-INFO
GoreUtilities.egg-info/SOURCES.txt
GoreUtilities.egg-info/dependency_links.txt
GoreUtilities.egg-info/top_level.txt
GoreUtilities/test/__init__.py
GoreUtilities/test/test_utils.py