Metadata-Version: 1.1
Name: GoreUtilities
Version: 0.4.0
Summary: Some utility functions useful for GoreLab members
Home-page: https://bitbucket.org/gorelab/goreutilities/
Author: Eugene Yurtsev, Jonathan Friedman
Author-email: eyurtsev@mit.edu
License: MIT
Download-URL: https://bitbucket.org/gorelab/goreutilities/get/v0.4.0.zip
Keywords: utility,plot,gorelab
Platform: UNKNOWN
